guillotina_graphql/__init__.py
guillotina_graphql/mappings.py
guillotina_graphql/schema.py
guillotina_graphql/services.py
guillotina_graphql/tests/__init__.py
guillotina_graphql/tests/conftest.py
guillotina_graphql/tests/fixtures.py
guillotina_graphql/tests/test_services.py
guillotina_graphql-0.1.1.dist-info/LICENSE
guillotina_graphql-0.1.1.dist-info/WHEEL
guillotina_graphql-0.1.1.dist-info/METADATA
guillotina_graphql-0.1.1.dist-info/RECORD
