Metadata-Version: 2.1
Name: guillotina-graphql
Version: 0.1.1
Summary: 
License: MIT
Author: Jordi Masip
Author-email: jordi@masip.cat
Requires-Python: >=3.7,<4.0
Classifier: License :: OSI Approved :: MIT License
Classifier: Programming Language :: Python :: 3
Classifier: Programming Language :: Python :: 3.7
Classifier: Programming Language :: Python :: 3.8
Requires-Dist: ariadne (>=0.12.0,<0.13.0)
Requires-Dist: guillotina (>=6.0.8,<7.0.0)
